uart_tx.v
`timescale 1ns / 1ps
//////////////////////////////////////////////////////////////////////////////////
// Company: 
// Engineer: 
// 
// Create Date: 14.02.2025 
// Design Name: 
// Module Name: uart_rx
// Project Name: uart_communication
// Target Devices: vsdsquadcom mini fpga board
// Tool Versions:  
// Description: 
// 
// Dependencies: 
// 
// Revision:
// Revision 0.01 - File Created
// Additional Comments:
// 
//////////////////////////////////////////////////////////////////////////////////

module uart_tx 
(
    input wire clk,           // System clock
    input wire rst,           // Reset
    input wire tx_start,      // Start transmission
    input wire [7:0] byte,    // 8-bit data to transmit
    input wire baud_rate_clk, // Baud rate clock
    output reg tx_out,        // UART TX output
    output reg tx_busy        // TX busy flag
);

    // UART FSM States
parameter [2:0] 
        IDLE  = 3'b000,  
        LOAD  = 3'b001,  
        START = 3'b010,  
        DATA  = 3'b011,  
        STOP  = 3'b100;
       reg [2:0]state;

    reg [7:0] shift_reg = 8'b0; // Shift register
    reg [3:0] bit_counter = 0;  // Bit counter

always @(posedge clk ) begin
            case (state)
                // IDLE State: Wait for Start Signal
                IDLE: begin
                    tx_out <= 1'b1;  // TX line stays HIGH
                    tx_busy <= 1'b0; // TX is idle
                    if (tx_start) begin
                        shift_reg <= byte;  // Load data
                        tx_busy <= 1'b1;    // TX is now busy
                        state <= LOAD;
                    end
                end

                //  LOAD State: Move Data into Shift Register
                LOAD: begin
                    state <= START;
                end

                // START State: Send Start Bit (0)
                START: begin
                    tx_out <= 1'b0; // Start bit
                    if (baud_rate_clk) begin
                        bit_counter <= 4'b0000;
                        state <= DATA;
                    end
                end

                //  DATA State: Transmit 8 Data Bits
                DATA: begin
                    if (baud_rate_clk) begin
                        tx_out <= shift_reg[0]; // Send LSB first
                        shift_reg <= shift_reg >> 1; // Shift data
                        bit_counter <= bit_counter + 1;
                        if (bit_counter == 7) begin
                            state <= STOP;
                        end
                    end
                end

                //  STOP State: Send Stop Bit (1)
                STOP: begin
                    if (baud_rate_clk) begin
                        tx_out <= 1'b1; // Stop bit
                        state <= IDLE;  // Go back to IDLE
                        tx_busy <= 1'b0; // TX is now idle
                    end
                end

                default: state <= IDLE;
            endcase
        end
endmodule

uart_tx_tb.v
`timescale 1ns / 1ps
//////////////////////////////////////////////////////////////////////////////////
// Company: BMSCE
// Engineer: K M SKANDA
// 
// Create Date: 14.02.2025
// Design Name: uart_communication
// Module Name: uart_tx_tb
// Project Name: UART Communication
// Target Devices: FPGA (VSD Squadcom Mini FPGA)
// Tool Versions: Open-source FPGA Tools (Yosys, NextPNR, IceStorm)
// Description: 
//      Testbench for the uart_tx. 
//
// Dependencies: 
//      Requires the `uart_tx` module.
//
// Revision:
// Revision 0.01 - File Created
// Additional Comments:
// 
//////////////////////////////////////////////////////////////////////////////////


//u can either include `inlcude "uart_tx.v" or u can runn both in terminal

module uart_tx_tb;
    reg clk;               // System clock
    reg rst;               // Reset
    reg tx_start;          // Start transmission
    reg [7:0] byte;        // Data to transmit
    reg baud_rate_clk;     // Baud rate clock
    wire tx_out;           // UART TX output
    wire tx_busy;          // TX busy flag

    // Instantiate the UART TX module
uart_tx uut (
        .clk(clk),
        .rst(rst),
        .tx_start(tx_start),
        .byte(byte),
        .baud_rate_clk(baud_rate_clk),
        .tx_out(tx_out),
        .tx_busy(tx_busy)
    );

    // Generate system clock (50 MHz example)
    always #10 clk = ~clk;  // 10 ns period → 100 MHz clock

    // Generate baud rate clock (115200 baud example)
    always #8680 baud_rate_clk = ~baud_rate_clk;  // 8680 ns period → ~115200 baud rate
    initial begin
    $dumpfile("uart_tx.vcd");  // Creates VCD file
    $dumpvars(0, uart_tx_tb);   // Dumps all signals of the testbench
    end

    initial begin
        // Initialize Signals
        clk = 0;
        baud_rate_clk = 0;
        rst = 1;
        tx_start = 0;
        byte = 8'b00000000;
        #50;  // Wait for reset stabilization

        // Release reset
        rst = 0;
        #50;

        // Test Case 1: Send Byte 0x55 (01010101)
        byte = 8'b01010101;
        tx_start = 1;
        #20;  // Small delay before disabling start signal
        tx_start = 0;

        // Wait for transmission to complete
        wait(tx_busy == 0);
        #10000; // Extra delay for stability

        // Test Case 2: Send Byte 0xA3 (10100011)
        byte = 8'b10100011;
        tx_start = 1;
        #20;
        tx_start = 0;

        // Wait for transmission to complete
        wait(tx_busy == 0);
        #10000;

        // Test Case 3: Send Byte 0xFF (11111111)
        byte = 8'b11111111;
        tx_start = 1;
        #20;
        tx_start = 0;

        // Wait for transmission to complete
        wait(tx_busy == 0);
        #10000;
        // End Simulation
        $finish;
    end

endmodule

uart_tx.vcd
$date
	Fri Feb 14 22:32:49 2025
$end
$version
	Icarus Verilog
$end
$timescale
	1ps
$end
$scope module uart_tx_tb $end
$var wire 1 ! tx_out $end
$var wire 1 " tx_busy $end
$var reg 1 # baud_rate_clk $end
$var reg 8 $ byte [7:0] $end
$var reg 1 % clk $end
$var reg 1 & rst $end
$var reg 1 ' tx_start $end
$scope module uut $end
$var wire 1 # baud_rate_clk $end
$var wire 8 ( byte [7:0] $end
$var wire 1 % clk $end
$var wire 1 & rst $end
$var wire 1 ' tx_start $end
$var parameter 3 ) DATA $end
$var parameter 3 * IDLE $end
$var parameter 3 + LOAD $end
$var parameter 3 , START $end
$var parameter 3 - STOP $end
$var reg 4 . bit_counter [3:0] $end
$var reg 8 / shift_reg [7:0] $end
$var reg 3 0 state [2:0] $end
$var reg 1 " tx_busy $end
$var reg 1 ! tx_out $end
$upscope $end
$upscope $end
$enddefinitions $end
$comment Show the parameter values. $end
$dumpall
b100 -
b10 ,
b1 +
b0 *
b11 )
$end
#0
$dumpvars
bx 0
b0 /
b0 .
b0 (
0'
1&
0%
b0 $
0#
x"
x!
$end
#10000
b0 0
1%
#20000
0%
#30000
0"
1!
1%
#40000
0%
#50000
1%
0&
#60000
0%
#70000
1%
#80000
0%
#90000
1%
#100000
0%
1'
b1010101 $
b1010101 (
#110000
b1 0
1"
b1010101 /
1%
#120000
0%
0'
#130000
b10 0
1%
#140000
0%
#150000
0!
1%
