uart_rx.v
//////////////////////////////////////////////////////////////////////////////////
// Company: BMSCE
// Engineer: K M SKANDA
// 
// Create Date: 14.02.2025
// Design Name: uart_communication
// Module Name: uart_rx
// Project Name: UART Communication
// Target Devices: FPGA (VSD Squadcom Mini FPGA)
// Tool Versions: Open-source FPGA Tools (Yosys, NextPNR, IceStorm)
// Revision:
// Revision 0.01 - File Created
// Additional Comments:
// 
//////////////////////////////////////////////////////////////////////////////////
`timescale 1ns / 1ps

module uart_rx (
    input wire clk,            // System Clock
    input wire rst,            // Reset
    input wire rx_serial,      // Serial RX Data Line
    input wire baud_rate_clk,  // Baud rate clock
    output reg [7:0] rx_byte,  // Received Byte Output
    output reg rx_done         // RX Complete Flag
);

    // FSM States
    parameter IDLE  = 3'b000;
    parameter START = 3'b001;
    parameter DATA  = 3'b010;
    parameter STOP  = 3'b011;
    parameter DONE  = 3'b100;

    reg [2:0] state = IDLE;     // Current State
    reg [3:0] bit_index = 0;    // Bit Counter
    reg [7:0] shift_reg = 0;    // Shift Register

    always @(posedge clk or posedge rst) begin
        if (rst) begin
            state <= IDLE;
            rx_done <= 0;
            rx_byte <= 8'b0;
            shift_reg <= 8'b0;
        end else begin
            case (state)
                IDLE: begin
                    rx_done <= 0;
                    if (rx_serial == 0)  // Start bit detected
                        state <= START;
                end

                START: begin
                    if (baud_rate_clk)
                        state <= DATA;
                end

                DATA: begin
                    if (baud_rate_clk) begin
                        shift_reg[bit_index] <= rx_serial;  // Sample data
                        bit_index <= bit_index + 1;
                        if (bit_index == 7) 
                            state <= STOP;
                    end
                end

                STOP: begin
                    if (baud_rate_clk) begin
                        if (rx_serial == 1) begin  // Valid stop bit
                            rx_byte <= shift_reg;
                            rx_done <= 1;
                            state <= DONE;
                        end else begin
                            state <= IDLE;  // Error detected, restart
                        end
                    end
                end

                DONE: begin
                    state <= IDLE;
                end

            endcase
        end
    end
endmodule

uart_tx.v
`timescale 1ns / 1ps
//////////////////////////////////////////////////////////////////////////////////
// Company: 
// Engineer: 
// 
// Create Date: 14.02.2025 
// Design Name: 
// Module Name: uart_rx
// Project Name: uart_communication
// Target Devices: vsdsquadcom mini fpga board
// Tool Versions:  
// Description: 
// 
// Dependencies: 
// 
// Revision:
// Revision 0.01 - File Created
// Additional Comments:
// 
//////////////////////////////////////////////////////////////////////////////////

module uart_tx 
(
    input wire clk,           // System clock
    input wire rst,           // Reset
    input wire tx_start,      // Start transmission
    input wire [7:0] byte,    // 8-bit data to transmit
    input wire baud_rate_clk, // Baud rate clock
    output reg tx_out,        // UART TX output
    output reg tx_busy        // TX busy flag
);

    // UART FSM States
parameter [2:0] 
        IDLE  = 3'b000,  
        LOAD  = 3'b001,  
        START = 3'b010,  
        DATA  = 3'b011,  
        STOP  = 3'b100;
       reg [2:0]state;

    reg [7:0] shift_reg = 8'b0; // Shift register
    reg [3:0] bit_counter = 0;  // Bit counter

always @(posedge clk ) begin
            case (state)
                // IDLE State: Wait for Start Signal
                IDLE: begin
                    tx_out <= 1'b1;  // TX line stays HIGH
                    tx_busy <= 1'b0; // TX is idle
                    if (tx_start) begin
                        shift_reg <= byte;  // Load data
                        tx_busy <= 1'b1;    // TX is now busy
                        state <= LOAD;
                    end
                end

                //  LOAD State: Move Data into Shift Register
                LOAD: begin
                    state <= START;
                end

                // START State: Send Start Bit (0)
                START: begin
                    tx_out <= 1'b0; // Start bit
                    if (baud_rate_clk) begin
                        bit_counter <= 4'b0000;
                        state <= DATA;
                    end
                end

                //  DATA State: Transmit 8 Data Bits
                DATA: begin
                    if (baud_rate_clk) begin
                        tx_out <= shift_reg[0]; // Send LSB first
                        shift_reg <= shift_reg >> 1; // Shift data
                        bit_counter <= bit_counter + 1;
                        if (bit_counter == 7) begin
                            state <= STOP;
                        end
                    end
                end

                //  STOP State: Send Stop Bit (1)
                STOP: begin
                    if (baud_rate_clk) begin
                        tx_out <= 1'b1; // Stop bit
                        state <= IDLE;  // Go back to IDLE
                        tx_busy <= 1'b0; // TX is now idle
                    end
                end

                default: state <= IDLE;
            endcase
        end
endmodule

uart.v
`timescale 1ns / 1ps
`include "uart_tx.v"
`include "uart_rx.v"
module uart (
    input wire clk,             // System Clock
    input wire rst,             // Reset Signal
    input wire tx_start,        // TX Start Signal
    input wire [7:0] tx_byte,   // Data to Transmit
    input wire rx_serial,       // RX Serial Data Line
    input wire baud_rate_clk,   // Shared Baud Rate Clock
    output wire tx_out,         // UART TX Output
    output wire tx_busy,        // TX Busy Flag
    output wire [7:0] rx_byte,  // Received Data
    output wire rx_done         // RX Done Flag
);

    // Instantiate UART TX Module
    uart_tx tx_inst (
        .clk(clk),
        .rst(rst),
        .tx_start(tx_start),
        .byte(tx_byte),
        .baud_rate_clk(baud_rate_clk),
        .tx_out(tx_out),
        .tx_busy(tx_busy)
    );

    // Instantiate UART RX Module
    uart_rx rx_inst (
        .clk(clk),
        .rst(rst),
        .rx_serial(rx_serial),
        .baud_rate_clk(baud_rate_clk),
        .rx_byte(rx_byte),
        .rx_done(rx_done)
    );

endmodule

uart_tb.v
//////////////////////////////////////////////////////////////////////////////////
// Company: BMSCE
// Engineer: K M SKANDA
// 
// Create Date: 14.02.2025
// Design Name: uart_communication
// Module Name: uart
// Project Name: UART Communication
// Target Devices: FPGA (VSD Squadcom Mini FPGA)
// Tool Versions: Open-source FPGA Tools (Yosys, NextPNR, IceStorm)
//
// Dependencies: 
//      Requires the uart module.
//
// Revision:
// Revision 0.01 - File Created
// Additional Comments:
// 
//////////////////////////////////////////////////////////////////////////////////
`timescale 1ns / 1ps
`include "uart.v"
module uart_full_duplex_tb;
    reg clk, rst, tx_start, rx_serial, baud_rate_clk;
    reg [7:0] tx_byte;
    wire tx_out, tx_busy;
    wire [7:0] rx_byte;
    wire rx_done;

    // Instantiate Full-Duplex UART Module
    uart uut (
        .clk(clk),
        .rst(rst),
        .tx_start(tx_start),
        .tx_byte(tx_byte),
        .rx_serial(rx_serial),
        .baud_rate_clk(baud_rate_clk),
        .tx_out(tx_out),
        .tx_busy(tx_busy),
        .rx_byte(rx_byte),
        .rx_done(rx_done)
    );

    always #10 clk = ~clk;  // 50 MHz System Clock
    always #8680 baud_rate_clk = ~baud_rate_clk;  // 115200 Baud Rate Clock

    initial begin
        $dumpfile("uart_full_duplex.vcd");
        $dumpvars(0, uart_full_duplex_tb);

        clk = 0; rst = 1; tx_start = 0; tx_byte = 8'h00; baud_rate_clk = 0;
        #50 rst = 0;

        // Test Case 1: TX Sends 0xA5, RX Receives It
        tx_byte = 8'hA5;
        tx_start = 1;
        #20 tx_start = 0;

        // Simulate receiving 0xA5 on rx_serial
        #8680 rx_serial = 0;  // Start Bit
        #8680 rx_serial = 1;  // Data Bit 0
        #8680 rx_serial = 0;  // Data Bit 1
        #8680 rx_serial = 1;  // Data Bit 2
        #8680 rx_serial = 0;  // Data Bit 3
        #8680 rx_serial = 1;  // Data Bit 4
        #8680 rx_serial = 0;  // Data Bit 5
        #8680 rx_serial = 1;  // Data Bit 6
        #8680 rx_serial = 1;  // Data Bit 7
        #8680 rx_serial = 1;  // Stop Bit

        #20000;
        $finish;
    end
endmodule

uart_full_duplex.vcd
$date
	Fri Feb 14 23:26:49 2025
$end
$version
	Icarus Verilog
$end
$timescale
	1ps
$end
$scope module uart_full_duplex_tb $end
$var wire 1 ! tx_out $end
$var wire 1 " tx_busy $end
$var wire 1 # rx_done $end
$var wire 8 $ rx_byte [7:0] $end
$var reg 1 % baud_rate_clk $end
$var reg 1 & clk $end
$var reg 1 ' rst $end
$var reg 1 ( rx_serial $end
$var reg 8 ) tx_byte [7:0] $end
$var reg 1 * tx_start $end
$scope module uut $end
$var wire 1 % baud_rate_clk $end
$var wire 1 & clk $end
$var wire 1 ' rst $end
$var wire 1 ( rx_serial $end
$var wire 8 + tx_byte [7:0] $end
$var wire 1 * tx_start $end
$var wire 1 ! tx_out $end
$var wire 1 " tx_busy $end
$var wire 1 # rx_done $end
$var wire 8 , rx_byte [7:0] $end
$scope module rx_inst $end
$var wire 1 % baud_rate_clk $end
$var wire 1 & clk $end
$var wire 1 ' rst $end
$var wire 1 ( rx_serial $end
$var parameter 3 - DATA $end
$var parameter 3 . DONE $end
$var parameter 3 / IDLE $end
$var parameter 3 0 START $end
$var parameter 3 1 STOP $end
$var reg 4 2 bit_index [3:0] $end
$var reg 8 3 rx_byte [7:0] $end
$var reg 1 # rx_done $end
$var reg 8 4 shift_reg [7:0] $end
$var reg 3 5 state [2:0] $end
$upscope $end
$scope module tx_inst $end
$var wire 1 % baud_rate_clk $end
$var wire 8 6 byte [7:0] $end
$var wire 1 & clk $end
$var wire 1 ' rst $end
$var wire 1 * tx_start $end
$var parameter 3 7 DATA $end
$var parameter 3 8 IDLE $end
$var parameter 3 9 LOAD $end
$var parameter 3 : START $end
$var parameter 3 ; STOP $end
$var reg 4 < bit_counter [3:0] $end
$var reg 8 = shift_reg [7:0] $end
$var reg 3 > state [2:0] $end
$var reg 1 " tx_busy $end
$var reg 1 ! tx_out $end
$upscope $end
$upscope $end
$upscope $end
$enddefinitions $end
$comment Show the parameter values. $end
$dumpall
b100 ;
b10 :
b1 9
b0 8
b11 7
b11 1
b1 0
b0 /
b100 .
b10 -
$end
#0
$dumpvars
bx >
b0 =
b0 <
b0 6
b0 5
b0 4
b0 3
b0 2
b0 ,
b0 +
0*
b0 )
x(
1'
0&
0%
b0 $
0#
x"
x!
$end
#10000
b0 >
1&
#20000
0&
#30000
0"
1!
1&
#40000
0&
#50000
b1 >
1"
b10100101 =
1&
1*
b10100101 )
b10100101 +
b10100101 6
0'
#60000
0&
#70000
b10 >
1&
0*
#80000
0&
#90000
0!
1&
#100000
0&
#110000
1&
#120000
0&
#130000
1&
#140000
0&
#150000
1&
#160000
0&
#170000
1&
#180000
0&
#190000
1&
#200000
0&
#210000
1&
#220000
0&
#230000
1&
#240000
0&
#250000
1&
#260000
0&
#270000
1&
#280000
0&
#290000
1&
#300000
0&
#310000
1&
#320000
0&
#330000
1&
#340000
0&
#350000
1&
#360000
0&
#370000
1&
#380000
0&
#390000
1&
#400000
0&
#410000
1&
#420000
0&
#430000
1&
#440000
0&
#450000
1&
#460000
0&
#470000
1&
#480000
0&
#490000
1&
#500000
0&
#510000
1&
#520000
0&
#530000
1&
#540000
0&
#550000
1&
#560000
0&
#570000
1&
#580000
0&
#590000
1&
#600000
0&
#610000
1&
#620000
0&
#630000
1&
#640000
0&
#650000
1&
#660000
0&
#670000
1&
#680000
0&
#690000
1&
#700000
0&
#710000
1&
#720000
0&
#730000
1&
#740000
0&
#750000
1&
#760000
0&
#770000
1&
#780000
0&
#790000
1&
#800000
0&
#810000
1&
#820000
0&
#830000
1&
#840000
0&
#850000
1&
#860000
0&
#870000
1&
#880000
0&
#890000
1&
#900000
0&
#910000
1&
#920000
0&
#930000
1&
#940000
0&
#950000
1&
#960000
0&
#970000
1&
#980000
0&
#990000
1&
#1000000
0&
#1010000
1&
#1020000
0&
#1030000
1&
#1040000
0&
#1050000
1&
#1060000
0&
#1070000
1&
#1080000
0&
#1090000
1&
#1100000
0&
#1110000
1&
#1120000
0&
#1130000
1&
#1140000
0&
#1150000
1&
#1160000
0&
#1170000
1&
#1180000
0&
#1190000
1&
#1200000
0&
#1210000
1&
#1220000
0&
#1230000
1&
#1240000
0&
#1250000
1&
#1260000
0&
#1270000
1&
#1280000
0&
#1290000
1&
#1300000
0&
#1310000
1&
#1320000
0&
#1330000
1&
#1340000
0&
#1350000
1&
#1360000
0&
#1370000
1&
#1380000
0&
#1390000
1&
#1400000
0&
#1410000
1&
#1420000
0&
#1430000
1&
#1440000
0&
#1450000
1&
#1460000
0&
#1470000
1&
#1480000
0&
#1490000
1&
#1500000
0&
#1510000
1&
#1520000
0&
#1530000
1&
#1540000
0&
#1550000
1&
#1560000
0&
#1570000
1&
#1580000
0&
#1590000
1&
#1600000
0&
#1610000
1&
#1620000
0&
#1630000
1&
#1640000
0&
#1650000
1&
#1660000
0&
#1670000
1&
#1680000
0&
#1690000
1&
#1700000
0&
#1710000
1&
#1720000
0&
#1730000
1&
#1740000
0&
#1750000
1&
#1760000
0&
#1770000
1&
#1780000
0&
#1790000
1&
#1800000
0&
#1810000
1&
#1820000
0&
#1830000
1&
#1840000
0&
#1850000
1&
#1860000
0&
#1870000
1&
#1880000
0&
#1890000
1&
#1900000
0&
#1910000
1&
#1920000
0&
#1930000
1&
#1940000
0&
#1950000
1&
#1960000
0&
#1970000
1&
#1980000
0&
#1990000
1&
#2000000
0&
#2010000
1&
#2020000
0&
#2030000
1&
#2040000
0&
#2050000
1&
#2060000
0&
#2070000
1&
#2080000
0&
#2090000
1&
#2100000
0&
#2110000
1&
#2120000
0&
#2130000
1&
#2140000
0&
#2150000
1&
#2160000
0&
#2170000
1&
#2180000
0&
#2190000
1&
#2200000
0&
#2210000
1&
#2220000
0&
#2230000
1&
#2240000
0&
#2250000
1&
#2260000
0&
#2270000
1&
#2280000
0&
#2290000
1&
#2300000
0&
#2310000
1&
#2320000
0&
#2330000
1&
#2340000
0&
#2350000
1&
#2360000
0&
#2370000
1&
#2380000
0&
#2390000
1&
#2400000
0&
#2410000
1&
#2420000
0&
#2430000
1&
#2440000
0&
#2450000
1&
#2460000
0&
#2470000
1&
#2480000
0&
#2490000
1&
#2500000
0&
#2510000
1&
#2520000
0&
#2530000
1&
#2540000
0&
#2550000
1&
#2560000
0&
#2570000
1&
#2580000
0&
#2590000
1&
#2600000
0&
#2610000
1&
#2620000
0&
#2630000
1&
#2640000
0&
#2650000
1&
#2660000
0&
#2670000
1&
#2680000
0&
#2690000
1&
#2700000
0&
#2710000
1&
#2720000
0&
#2730000
1&
#2740000
0&
#2750000
1&
#2760000
0&
#2770000
1&
#2780000
0&
#2790000
1&
#2800000
0&
#2810000
1&
#2820000
0&
#2830000
1&
#2840000
0&
#2850000
1&
#2860000
0&
#2870000
1&
#2880000
0&
#2890000
1&
#2900000
0&
#2910000
1&
#2920000
0&
#2930000
1&
#2940000
0&
#2950000
1&
#2960000
0&
#2970000
1&
#2980000
0&
#2990000
1&
#3000000
0&
#3010000
1&
#3020000
0&
#3030000
1&
#3040000
0&
#3050000
1&
#3060000
0&
#3070000
1&
#3080000
0&
#3090000
1&
#3100000
0&
#3110000
1&
#3120000
0&
#3130000
1&
#3140000
0&
#3150000
1&
#3160000
0&
#3170000
1&
#3180000
0&
#3190000
1&
#3200000
0&
#3210000
1&
#3220000
0&
#3230000
1&
#3240000
0&
#3250000
1&
#3260000
0&
#3270000
1&
#3280000
0&
#3290000
1&
#3300000
0&
#3310000
1&
#3320000
0&
#3330000
1&
#3340000
0&
#3350000
1&
#3360000
0&
#3370000
1&
#3380000
0&
#3390000
1&
#3400000
0&
#3410000
1&
#3420000
0&
#3430000
1&
#3440000
0&
#3450000
1&
#3460000
0&
#3470000
1&
#3480000
0&
#3490000
1&
#3500000
0&
#3510000
1&
#3520000
0&
#3530000
1&
#3540000
0&
#3550000
1&
#3560000
0&
#3570000
1&
#3580000
0&
#3590000
1&
#3600000
0&
#3610000
1&
#3620000
0&
#3630000
1&
#3640000
0&
#3650000
1&
#3660000
0&
#3670000
1&
#3680000
0&
#3690000
1&
#3700000
0&
#3710000
1&
#3720000
0&
#3730000
1&
#3740000
0&
#3750000
1&
#3760000
0&
#3770000
1&
#3780000
0&
#3790000
1&
#3800000
0&
#3810000
1&
#3820000
0&
#3830000
1&
#3840000
0&
#3850000
1&
#3860000
0&
#3870000
1&
#3880000
0&
#3890000
1&
#3900000
0&
#3910000
1&
#3920000
0&
#3930000
1&
#3940000
0&
#3950000
1&
#3960000
0&
#3970000
1&
#3980000
0&
#3990000
1&
#4000000
0&
#4010000
1&
#4020000
0&
#4030000
1&
#4040000
0&
#4050000
1&
#4060000
0&
#4070000
1&
#4080000
0&
#4090000
1&
#4100000
0&
#4110000
1&
#4120000
0&
#4130000
1&
#4140000
0&
#4150000
1&
#4160000
0&
#4170000
1&
#4180000
0&
#4190000
1&
#4200000
0&
#4210000
1&
#4220000
0&
#4230000
1&
#4240000
0&
#4250000
1&
#4260000
0&
#4270000
1&
#4280000
0&
#4290000
1&
#4300000
0&
#4310000
1&
#4320000
0&
#4330000
1&
#4340000
0&
#4350000
1&
#4360000
0&
#4370000
1&
#4380000
0&
#4390000
1&
#4400000
0&
#4410000
1&
#4420000
0&
#4430000
1&
#4440000
0&
#4450000
1&
#4460000
0&
#4470000
1&
#4480000
0&
#4490000
1&
#4500000
0&
#4510000
1&
#4520000
0&
#4530000
1&
#4540000
0&
#4550000
1&
#4560000
0&
#4570000
1&
#4580000
0&
#4590000
1&
#4600000
0&
#4610000
1&
#4620000
0&
#4630000
1&
#4640000
0&
#4650000
1&
#4660000
0&
#4670000
1&
#4680000
0&
#4690000
1&
#4700000
0&
#4710000
1&
#4720000
0&
#4730000
1&
#4740000
0&
#4750000
1&
#4760000
0&
#4770000
1&
#4780000
0&
#4790000
1&
#4800000
0&
#4810000
1&
#4820000
0&
#4830000
1&
#4840000
0&
#4850000
1&
#4860000
0&
#4870000
1&
#4880000
0&
#4890000
1&
#4900000
0&
#4910000
1&
#4920000
0&
#4930000
1&
#4940000
0&
#4950000
1&
#4960000
0&
#4970000
1&
#4980000
0&
#4990000
1&
#5000000
0&
#5010000
1&
#5020000
0&
#5030000
1&
#5040000
0&
#5050000
1&
#5060000
0&
#5070000
1&
#5080000
0&
#5090000
1&
#5100000
0&
#5110000
1&
#5120000
0&
#5130000
1&
#5140000
0&
#5150000
1&
#5160000
0&
#5170000
1&
#5180000
0&
#5190000
1&
#5200000
0&
#5210000
1&
#5220000
0&
#5230000
1&
#5240000
0&
#5250000
1&
#5260000
0&
#5270000
1&
#5280000
0&
#5290000
1&
#5300000
0&
#5310000
1&
#5320000
0&
#5330000
1&
#5340000
0&
#5350000
1&
#5360000
0&
#5370000
1&
#5380000
0&
#5390000
1&
#5400000
0&
#5410000
1&
#5420000
0&
#5430000
1&
#5440000
0&
#5450000
1&
#5460000
0&
#5470000
1&
#5480000
0&
#5490000
1&
#5500000
0&
#5510000
1&
#5520000
0&
#5530000
1&
#5540000
0&
#5550000
1&
#5560000
0&
#5570000
1&
#5580000
0&
#5590000
1&
#5600000
0&
#5610000
1&
#5620000
0&
#5630000
1&
#5640000
0&
#5650000
1&
#5660000
0&
#5670000
1&
#5680000
0&
#5690000
1&
#5700000
0&
#5710000
1&
#5720000
0&
#5730000
1&
#5740000
0&
#5750000
1&
#5760000
0&
#5770000
1&
#5780000
0&
#5790000
1&
#5800000
0&
#5810000
1&
#5820000
0&
#5830000
1&
#5840000
0&
#5850000
1&
#5860000
0&
#5870000
1&
#5880000
0&
#5890000
1&
#5900000
0&
#5910000
1&
#5920000
0&
#5930000
1&
#5940000
0&
#5950000
1&
#5960000
0&
#5970000
1&
#5980000
0&
#5990000
1&
#6000000
0&
#6010000
1&
#6020000
0&
#6030000
1&
#6040000
0&
#6050000
1&
#6060000
0&
#6070000
1&
#6080000
0&
#6090000
1&
#6100000
0&
#6110000
1&
#6120000
0&
#6130000
1&
#6140000
0&
#6150000
1&
#6160000
0&
#6170000
1&
#6180000
0&
#6190000
1&
#6200000
0&
#6210000
1&
#6220000
0&
#6230000
1&
#6240000
0&
#6250000
1&
#6260000
0&
#6270000
1&
#6280000
0&
#6290000
1&
#6300000
0&
#6310000
1&
#6320000
0&
#6330000
1&
#6340000
0&
#6350000
1&
#6360000
0&
#6370000
1&
#6380000
0&
#6390000
1&
#6400000
0&
#6410000
1&
#6420000
0&
#6430000
1&
#6440000
0&
#6450000
1&
#6460000
0&
#6470000
1&
#6480000
0&
#6490000
1&
#6500000
0&
#6510000
1&
#6520000
0&
#6530000
1&
#6540000
0&
#6550000
1&
#6560000
0&
#6570000
1&
#6580000
0&
#6590000
1&
#6600000
0&
#6610000
1&
#6620000
0&
#6630000
1&
#6640000
0&
#6650000
1&
#6660000
0&
#6670000
1&
#6680000
0&
#6690000
1&
#6700000
0&
#6710000
1&
#6720000
0&
#6730000
1&
#6740000
0&
#6750000
1&
#6760000
0&
#6770000
1&
#6780000
0&
#6790000
1&
#6800000
0&
#6810000
1&
#6820000
0&
#6830000
1&
#6840000
0&
#6850000
1&
#6860000
0&
#6870000
1&
#6880000
0&
#6890000
1&
#6900000
0&
#6910000
1&
#6920000
0&
#6930000
1&
#6940000
0&
#6950000
1&
#6960000
0&
#6970000
1&
#6980000
0&
#6990000
1&
#7000000
0&
#7010000
1&
#7020000
0&
#7030000
1&
#7040000
0&
#7050000
1&
#7060000
0&
#7070000
1&
#7080000
0&
#7090000
1&
#7100000
0&
#7110000
1&
#7120000
0&
#7130000
1&
#7140000
0&
#7150000
1&
#7160000
0&
#7170000
1&
#7180000
0&
#7190000
1&
#7200000
0&
#7210000
1&
#7220000
0&
#7230000
1&
#7240000
0&
#7250000
1&
#7260000
0&
#7270000
1&
#7280000
0&
#7290000
1&
#7300000
0&
#7310000
1&
#7320000
0&
#7330000
1&
#7340000
0&
#7350000
1&
#7360000
0&
#7370000
1&
#7380000
0&
#7390000
1&
#7400000
0&
#7410000
1&
#7420000
0&
#7430000
1&
#7440000
0&
#7450000
1&
#7460000
0&
#7470000
1&
#7480000
0&
#7490000
1&
#7500000
0&
#7510000
1&
#7520000
0&
#7530000
1&
#7540000
0&
#7550000
1&
#7560000
0&
#7570000
1&
#7580000
0&
#7590000
1&
#7600000
0&
#7610000
1&
#7620000
0&
#7630000
1&
#7640000
0&
#7650000
1&
#7660000
0&
#7670000
1&
#7680000
0&
#7690000
1&
#7700000
0&
#7710000
1&
#7720000
0&
#7730000
1&
#7740000
0&
#7750000
1&
#7760000
0&
#7770000
1&
#7780000
0&
#7790000
1&
#7800000
0&
#7810000
1&
#7820000
0&
#7830000
1&
#7840000
0&
#7850000
1&
#7860000
0&
#7870000
1&
#7880000
0&
#7890000
1&
#7900000
0&
#7910000
1&
#7920000
0&
#7930000
1&
#7940000
0&
#7950000
1&
#7960000
0&
#7970000
1&
#7980000
0&
#7990000
1&
#8000000
0&
#8010000
1&
#8020000
0&
#8030000
1&
#8040000
0&
#8050000
1&
#8060000
0&
#8070000
1&
#8080000
0&
#8090000
1&
#8100000
0&
#8110000
1&
#8120000
0&
#8130000
1&
#8140000
0&
#8150000
1&
#8160000
0&
#8170000
1&
#8180000
0&
#8190000
1&
#8200000
0&
#8210000
1&
#8220000
0&
#8230000
1&
#8240000
0&
#8250000
1&
#8260000
0&
#8270000
1&
#8280000
0&
#8290000
1&
#8300000
0&
#8310000
1&
#8320000
0&
#8330000
1&
#8340000
0&
#8350000
1&
#8360000
0&
#8370000
1&
#8380000
0&
#8390000
1&
#8400000
0&
#8410000
1&
#8420000
0&
#8430000
1&
#8440000
0&
#8450000
1&
#8460000
0&
#8470000
1&
#8480000
0&
#8490000
1&
#8500000
0&
#8510000
1&
#8520000
0&
#8530000
1&
#8540000
0&
#8550000
1&
#8560000
0&
#8570000
1&
#8580000
0&
#8590000
1&
#8600000
0&
#8610000
1&
#8620000
0&
#8630000
1&
#8640000
0&
#8650000
1&
#8660000
0&
#8670000
1&
#8680000
0&
1%
#8690000
b11 >
1&
#8700000
0&
#8710000
b1 <
b1010010 =
1!
1&
#8720000
0&
#8730000
b10 <
b101001 =
0!
1&
#8740000
0&
#8750000
b1 5
b11 <
b10100 =
1!
1&
0(
#8760000
0&
#8770000
b10 5
b100 <
b1010 =
0!
1&
#8780000
0&
#8790000
b1 2
b101 <
b101 =
1&
#8800000
0&
#8810000
b10 2
b110 <
b10 =
1!
1&
#8820000
0&
#8830000
b11 2
b111 <
b1 =
0!
1&
#8840000
0&
#8850000
b100 2
b100 >
b1000 <
b0 =
1!
1&
#8860000
0&
#8870000
b101 2
0"
b0 >
1&
#8880000
0&
#8890000
b110 2
1&
#8900000
0&
#8910000
b111 2
1&
#8920000
0&
#8930000
b11 5
b1000 2
1&
#8940000
0&
#8950000
b0 5
1&
#8960000
0&
#8970000
b1 5
1&
#8980000
0&
#8990000
b10 5
1&
#9000000
0&
#9010000
b1001 2
1&
#9020000
0&
#9030000
b1010 2
1&
#9040000
0&
#9050000
b1011 2
1&
#9060000
0&
#9070000
b1100 2
1&
#9080000
0&
#9090000
b1101 2
1&
#9100000
0&
#9110000
b1110 2
1&
#9120000
0&
#9130000
b1111 2
1&
#9140000
0&
#9150000
b0 2
1&
#9160000
0&
#9170000
b1 2
1&
#9180000
0&
#9190000
b10 2
1&
#9200000
0&
#9210000
b11 2
1&
#9220000
0&
#9230000
b100 2
1&
#9240000
0&
#9250000
b101 2
1&
#9260000
0&
#9270000
b110 2
1&
#9280000
0&
#9290000
b111 2
1&
#9300000
0&
#9310000
b11 5
b1000 2
1&
#9320000
0&
#9330000
b0 5
1&
#9340000
0&
#9350000
b1 5
1&
#9360000
0&
#9370000
b10 5
1&
#9380000
0&
#9390000
b1001 2
1&
#9400000
0&
#9410000
b1010 2
1&
#9420000
0&
#9430000
b1011 2
1&
#9440000
0&
#9450000
b1100 2
1&
#9460000
0&
#9470000
b1101 2
1&
#9480000
0&
#9490000
b1110 2
1&
#9500000
0&
#9510000
b1111 2
1&
#9520000
0&
#9530000
b0 2
1&
#9540000
0&
#9550000
b1 2
1&
#9560000
0&
#9570000
b10 2
1&
#9580000
0&
#9590000
b11 2
1&
#9600000
0&
#9610000
b100 2
1&
#9620000
0&
#9630000
b101 2
1&
#9640000
0&
#9650000
b110 2
1&
#9660000
0&
#9670000
b111 2
1&
#9680000
0&
#9690000
b11 5
b1000 2
1&
#9700000
0&
#9710000
b0 5
1&
#9720000
0&
#9730000
b1 5
1&
#9740000
0&
#9750000
b10 5
1&
#9760000
0&
#9770000
b1001 2
1&
#9780000
0&
#9790000
b1010 2
1&
#9800000
0&
#9810000
b1011 2
1&
#9820000
0&
#9830000
b1100 2
1&
#9840000
0&
#9850000
b1101 2
1&
#9860000
0&
#9870000
b1110 2
1&
#9880000
0&
#9890000
b1111 2
1&
#9900000
0&
#9910000
b0 2
1&
#9920000
0&
#9930000
b1 2
1&
#9940000
0&
#9950000
b10 2
1&
#9960000
0&
#9970000
b11 2
1&
#9980000
0&
#9990000
b100 2
1&
#10000000
0&
#10010000
b101 2
1&
#10020000
0&
#10030000
b110 2
1&
#10040000
0&
#10050000
b111 2
1&
#10060000
0&
#10070000
b11 5
b1000 2
1&
#10080000
0&
#10090000
b0 5
1&
#10100000
0&
#10110000
b1 5
1&
#10120000
0&
#10130000
b10 5
1&
#10140000
0&
#10150000
b1001 2
1&
#10160000
0&
#10170000
b1010 2
1&
#10180000
0&
#10190000
b1011 2
1&
#10200000
0&
#10210000
b1100 2
1&
#10220000
0&
#10230000
b1101 2
1&
#10240000
0&
#10250000
b1110 2
1&
#10260000
0&
#10270000
b1111 2
1&
#10280000
0&
#10290000
b0 2
1&
#10300000
0&
#10310000
b1 2
1&
#10320000
0&
#10330000
b10 2
1&
#10340000
0&
#10350000
b11 2
1&
#10360000
0&
#10370000
b100 2
1&
#10380000
0&
#10390000
b101 2
1&
#10400000
0&
#10410000
b110 2
1&
#10420000
0&
#10430000
b111 2
1&
#10440000
0&
#10450000
b11 5
b1000 2
1&
#10460000
0&
#10470000
b0 5
1&
#10480000
0&
#10490000
b1 5
1&
#10500000
0&
#10510000
b10 5
1&
#10520000
0&
#10530000
b1001 2
1&
#10540000
0&
#10550000
b1010 2
1&
#10560000
0&
#10570000
b1011 2
1&
#10580000
0&
#10590000
b1100 2
1&
#10600000
0&
#10610000
b1101 2
1&
#10620000
0&
#10630000
b1110 2
1&
#10640000
0&
#10650000
b1111 2
1&
#10660000
0&
#10670000
b0 2
1&
#10680000
0&
#10690000
b1 2
1&
#10700000
0&
#10710000
b10 2
1&
#10720000
0&
#10730000
b11 2
1&
#10740000
0&
#10750000
b100 2
1&
#10760000
0&
#10770000
b101 2
1&
#10780000
0&
#10790000
b110 2
1&
#10800000
0&
#10810000
b111 2
1&
#10820000
0&
#10830000
b11 5
b1000 2
1&
#10840000
0&
#10850000
b0 5
1&
#10860000
0&
#10870000
b1 5
1&
#10880000
0&
#10890000
b10 5
1&
#10900000
0&
#10910000
b1001 2
1&
#10920000
0&
#10930000
b1010 2
1&
#10940000
0&
#10950000
b1011 2
1&
#10960000
0&
#10970000
b1100 2
1&
#10980000
0&
#10990000
b1101 2
1&
#11000000
0&
#11010000
b1110 2
1&
#11020000
0&
#11030000
b1111 2
1&
#11040000
0&
#11050000
b0 2
1&
#11060000
0&
#11070000
b1 2
1&
#11080000
0&
#11090000
b10 2
1&
#11100000
0&
#11110000
b11 2
1&
#11120000
0&
#11130000
b100 2
1&
#11140000
0&
#11150000
b101 2
1&
#11160000
0&
#11170000
b110 2
1&
#11180000
0&
#11190000
b111 2
1&
#11200000
0&
#11210000
b11 5
b1000 2
1&
#11220000
0&
#11230000
b0 5
1&
#11240000
0&
#11250000
b1 5
1&
#11260000
0&
#11270000
b10 5
1&
#11280000
0&
#11290000
b1001 2
1&
#11300000
0&
#11310000
b1010 2
1&
#11320000
0&
#11330000
b1011 2
1&
#11340000
0&
#11350000
b1100 2
1&
#11360000
0&
#11370000
b1101 2
1&
#11380000
0&
#11390000
b1110 2
1&
#11400000
0&
#11410000
b1111 2
1&
#11420000
0&
#11430000
b0 2
1&
#11440000
0&
#11450000
b1 2
1&
#11460000
0&
#11470000
b10 2
1&
#11480000
0&
#11490000
b11 2
1&
#11500000
0&
#11510000
b100 2
1&
#11520000
0&
#11530000
b101 2
1&
#11540000
0&
#11550000
b110 2
1&
#11560000
0&
#11570000
b111 2
1&
#11580000
0&
#11590000
b11 5
b1000 2
1&
#11600000
0&
#11610000
b0 5
1&
#11620000
0&
#11630000
b1 5
1&
#11640000
0&
#11650000
b10 5
1&
